msslib/__init__.py
msslib/msslib.py
msslib-0.1.2.dist-info/METADATA
msslib-0.1.2.dist-info/WHEEL
msslib-0.1.2.dist-info/licenses/LICENSE.md
msslib-0.1.2.dist-info/RECORD
