Metadata-Version: 2.1
Name: msslib
Version: 0.1.2
Summary: A python port of Justin Braaten's msslib: https://github.com/gee-community/msslib
Project-URL: Homepage, https://github.com/boothmanrylan/msslib
Author-email: Rylan Boothman <boothmanrylan@gmail.com>
License-File: LICENSE.md
Classifier: License :: OSI Approved :: Apache Software License
Classifier: Operating System :: OS Independent
Classifier: Programming Language :: Python :: 3
Requires-Python: >=3.7
Requires-Dist: earthengine-api
Requires-Dist: ipython
